spott/__init__.py
spott/recognizer.py
spott-1.dist-info/METADATA
spott-1.dist-info/WHEEL
spott-1.dist-info/top_level.txt
spott-1.dist-info/RECORD
